beekeeper/embeddings/watsonx/__init__.py
beekeeper/embeddings/watsonx/base.py
beekeeper_embeddings_watsonx-1.0.2.dist-info/METADATA
beekeeper_embeddings_watsonx-1.0.2.dist-info/WHEEL
beekeeper_embeddings_watsonx-1.0.2.dist-info/RECORD
