Metadata-Version: 2.4
Name: beekeeper-embeddings-watsonx
Version: 1.0.2
Summary: beekeeper embeddings watsonx extension
Author-email: Leonardo Furnielis <leonardofurnielis@outlook.com>
License: Apache-2.0
Requires-Python: <4.0,>=3.10
Requires-Dist: beekeeper-core<2.0.0,>=1.0.3
Requires-Dist: ibm-watsonx-ai<2.0.0,>=1.3.26
Provides-Extra: dev
Requires-Dist: ruff>=0.11.13; extra == 'dev'
